nxvalidate/__init__.py
nxvalidate/_version.py
nxvalidate/utils.py
nxvalidate/validate.py
nxvalidate/definitions/applications/NXarchive.nxdl.xml
nxvalidate/definitions/applications/NXarpes.nxdl.xml
nxvalidate/definitions/applications/NXcanSAS.nxdl.xml
nxvalidate/definitions/applications/NXdirecttof.nxdl.xml
nxvalidate/definitions/applications/NXfluo.nxdl.xml
nxvalidate/definitions/applications/NXindirecttof.nxdl.xml
nxvalidate/definitions/applications/NXiqproc.nxdl.xml
nxvalidate/definitions/applications/NXlauetof.nxdl.xml
nxvalidate/definitions/applications/NXmonopd.nxdl.xml
nxvalidate/definitions/applications/NXmx.nxdl.xml
nxvalidate/definitions/applications/NXrefscan.nxdl.xml
nxvalidate/definitions/applications/NXreftof.nxdl.xml
nxvalidate/definitions/applications/NXsas.nxdl.xml
nxvalidate/definitions/applications/NXsastof.nxdl.xml
nxvalidate/definitions/applications/NXscan.nxdl.xml
nxvalidate/definitions/applications/NXspe.nxdl.xml
nxvalidate/definitions/applications/NXsqom.nxdl.xml
nxvalidate/definitions/applications/NXstxm.nxdl.xml
nxvalidate/definitions/applications/NXtas.nxdl.xml
nxvalidate/definitions/applications/NXtofnpd.nxdl.xml
nxvalidate/definitions/applications/NXtofraw.nxdl.xml
nxvalidate/definitions/applications/NXtofsingle.nxdl.xml
nxvalidate/definitions/applications/NXtomo.nxdl.xml
nxvalidate/definitions/applications/NXtomophase.nxdl.xml
nxvalidate/definitions/applications/NXtomoproc.nxdl.xml
nxvalidate/definitions/applications/NXxas.nxdl.xml
nxvalidate/definitions/applications/NXxasproc.nxdl.xml
nxvalidate/definitions/applications/NXxbase.nxdl.xml
nxvalidate/definitions/applications/NXxeuler.nxdl.xml
nxvalidate/definitions/applications/NXxkappa.nxdl.xml
nxvalidate/definitions/applications/NXxlaue.nxdl.xml
nxvalidate/definitions/applications/NXxlaueplate.nxdl.xml
nxvalidate/definitions/applications/NXxnb.nxdl.xml
nxvalidate/definitions/applications/NXxrot.nxdl.xml
nxvalidate/definitions/base_classes/NXaperture.nxdl.xml
nxvalidate-0.3.5b3.dist-info/COPYING
nxvalidate-0.3.5b3.dist-info/METADATA
nxvalidate-0.3.5b3.dist-info/WHEEL
nxvalidate-0.3.5b3.dist-info/entry_points.txt
nxvalidate-0.3.5b3.dist-info/top_level.txt
nxvalidate-0.3.5b3.dist-info/RECORD
