Metadata-Version: 2.1
Name: nxvalidate
Version: 0.3.5b3
Summary: A Python package for validating NeXus files
License: Licensing Terms for NeXpy Packages
Project-URL: Repository, https://github.com/nexpy/nxvalidate.git
Project-URL: Issues, https://github.com/nexpy/nxvalidate/issues
Keywords: data format,HDF5,neutron scattering,x-ray scattering
Classifier: Development Status :: 4 - Beta
Classifier: License :: OSI Approved :: MIT License
Classifier: Programming Language :: Python :: 3
Classifier: Programming Language :: Python :: 3.8
Classifier: Programming Language :: Python :: 3.9
Classifier: Programming Language :: Python :: 3.10
Classifier: Programming Language :: Python :: 3.11
Classifier: Programming Language :: Python :: 3.12
Requires-Python: >=3.8
License-File: COPYING
Requires-Dist: nexusformat
Requires-Dist: colored >=2.0.0
Requires-Dist: importlib-resources ; python_version <= "3.9"
Provides-Extra: test
Requires-Dist: pytest ; extra == 'test'
